{
	"textures": {
		"0": "animated_java:blueprint/t_rex/t_rex",
		"particle": "minecraft:item/pufferfish"
	},
	"display": {
		"head": {
			"rotation": [0, 180, 0]
		}
	},
	"elements": [
		{
			"from": [3.83132, 2.64207, -6.00439],
			"to": [12.17013, 11.34337, 7.04684],
			"rotation": {
				"angle": 17.5,
				"axis": "x",
				"origin": [9.8132, -0.98215, 9.94607]
			},
			"faces": {
				"north": {
					"uv": [1.9, 6, 3, 7.2],
					"texture": "#0"
				},
				"east": {
					"uv": [0.1, 6, 1.9, 7.2],
					"texture": "#0"
				},
				"south": {
					"uv": [4.8, 6, 5.9, 7.2],
					"texture": "#0"
				},
				"west": {
					"uv": [3, 6, 4.8, 7.2],
					"texture": "#0"
				},
				"up": {
					"uv": [3, 6, 1.9, 4.2],
					"texture": "#0"
				},
				"down": {
					"uv": [4.1, 4.2, 3, 6],
					"texture": "#0"
				}
			}
		},
		{
			"from": [3.82407, 7.23151, -9.47946],
			"to": [12.17593, 15.58337, -1.49009],
			"rotation": {
				"angle": 0,
				"axis": "y",
				"origin": [9.81247, 3.61382, 1.40261]
			},
			"faces": {
				"north": {
					"uv": [9.7, 1.1, 10.8, 2.2],
					"texture": "#0"
				},
				"east": {
					"uv": [8.6, 1.1, 9.7, 2.2],
					"texture": "#0"
				},
				"south": {
					"uv": [11.9, 1.1, 13, 2.2],
					"texture": "#0"
				},
				"west": {
					"uv": [10.8, 1.1, 11.9, 2.2],
					"texture": "#0"
				},
				"up": {
					"uv": [10.8, 1.1, 9.7, 0],
					"texture": "#0"
				},
				"down": {
					"uv": [11.9, 0, 10.8, 1.1],
					"texture": "#0"
				}
			}
		},
		{
			"from": [4.19091, 10.49831, -16],
			"to": [11.80909, 15.39778, -9.46931],
			"rotation": {
				"angle": 0,
				"axis": "y",
				"origin": [9.44998, 4.15756, -6.57226]
			},
			"faces": {
				"north": {
					"uv": [9.5, 3.2, 10.5, 3.8],
					"texture": "#0"
				},
				"east": {
					"uv": [8.6, 3.2, 9.5, 3.8],
					"texture": "#0"
				},
				"south": {
					"uv": [11.4, 3.2, 12.4, 3.8],
					"texture": "#0"
				},
				"west": {
					"uv": [10.5, 3.2, 11.4, 3.8],
					"texture": "#0"
				},
				"up": {
					"uv": [10.5, 3.2, 9.5, 2.3],
					"texture": "#0"
				},
				"down": {
					"uv": [11.5, 2.3, 10.5, 3.2],
					"texture": "#0"
				}
			}
		},
		{
			"from": [4.19164, 9.5928, -11.64935],
			"to": [11.80836, 12.67835, -5.12011],
			"rotation": {
				"angle": -22.5,
				"axis": "x",
				"origin": [9.44998, 0.71387, -2.22233]
			},
			"faces": {
				"north": {
					"uv": [10.7, 12.2, 11.7, 12.6],
					"texture": "#0"
				},
				"east": {
					"uv": [9.8, 12.2, 10.7, 12.6],
					"texture": "#0"
				},
				"south": {
					"uv": [12.6, 12.2, 13.6, 12.6],
					"texture": "#0"
				},
				"west": {
					"uv": [11.7, 12.2, 12.6, 12.6],
					"texture": "#0"
				},
				"up": {
					"uv": [11.7, 12.2, 10.7, 11.3],
					"texture": "#0"
				},
				"down": {
					"uv": [12.7, 11.3, 11.7, 12.2],
					"texture": "#0"
				}
			}
		},
		{
			"from": [11.44152, 6.87409, -14.91179],
			"to": [11.62711, 7.42218, -14.3637],
			"rotation": {
				"angle": 22.5,
				"axis": "x",
				"origin": [11.62494, 7.60126, -10.92218]
			},
			"faces": {
				"north": {
					"uv": [5.8, 7.9, 5.8, 7.9],
					"texture": "#0"
				},
				"east": {
					"uv": [5.8, 7.9, 5.8, 7.9],
					"texture": "#0"
				},
				"south": {
					"uv": [5.8, 7.9, 5.8, 7.9],
					"texture": "#0"
				},
				"west": {
					"uv": [5.8, 7.9, 5.8, 7.9],
					"texture": "#0"
				},
				"up": {
					"uv": [5.8, 7.9, 5.8, 7.9],
					"texture": "#0"
				},
				"down": {
					"uv": [5.8, 7.9, 5.8, 7.9],
					"texture": "#0"
				}
			}
		},
		{
			"from": [11.44152, 7.23659, -14.00556],
			"to": [11.62711, 7.78468, -13.45747],
			"rotation": {
				"angle": 22.5,
				"axis": "x",
				"origin": [11.62494, 7.96375, -10.01595]
			},
			"faces": {
				"north": {
					"uv": [5.8, 7.9, 5.8, 7.9],
					"texture": "#0"
				},
				"east": {
					"uv": [5.8, 7.9, 5.8, 7.9],
					"texture": "#0"
				},
				"south": {
					"uv": [5.8, 7.9, 5.8, 7.9],
					"texture": "#0"
				},
				"west": {
					"uv": [5.8, 7.9, 5.8, 7.9],
					"texture": "#0"
				},
				"up": {
					"uv": [5.8, 7.9, 5.8, 7.9],
					"texture": "#0"
				},
				"down": {
					"uv": [5.8, 7.9, 5.8, 7.9],
					"texture": "#0"
				}
			}
		},
		{
			"from": [11.44152, 7.59908, -13.09932],
			"to": [11.62711, 8.14717, -12.55123],
			"rotation": {
				"angle": 22.5,
				"axis": "x",
				"origin": [11.62494, 8.32624, -9.10971]
			},
			"faces": {
				"north": {
					"uv": [5.8, 7.9, 5.8, 7.9],
					"texture": "#0"
				},
				"east": {
					"uv": [5.8, 7.9, 5.8, 7.9],
					"texture": "#0"
				},
				"south": {
					"uv": [5.8, 7.9, 5.8, 7.9],
					"texture": "#0"
				},
				"west": {
					"uv": [5.8, 7.9, 5.8, 7.9],
					"texture": "#0"
				},
				"up": {
					"uv": [5.8, 7.9, 5.8, 7.9],
					"texture": "#0"
				},
				"down": {
					"uv": [5.8, 7.9, 5.8, 7.9],
					"texture": "#0"
				}
			}
		},
		{
			"from": [11.44152, 7.96158, -12.19309],
			"to": [11.62711, 8.50967, -11.645],
			"rotation": {
				"angle": 22.5,
				"axis": "x",
				"origin": [11.62494, 8.68874, -8.20348]
			},
			"faces": {
				"north": {
					"uv": [5.8, 7.9, 5.8, 7.9],
					"texture": "#0"
				},
				"east": {
					"uv": [5.8, 7.9, 5.8, 7.9],
					"texture": "#0"
				},
				"south": {
					"uv": [5.8, 7.9, 5.8, 7.9],
					"texture": "#0"
				},
				"west": {
					"uv": [5.8, 7.9, 5.8, 7.9],
					"texture": "#0"
				},
				"up": {
					"uv": [5.8, 7.9, 5.8, 7.9],
					"texture": "#0"
				},
				"down": {
					"uv": [5.8, 7.9, 5.8, 7.9],
					"texture": "#0"
				}
			}
		},
		{
			"from": [11.44152, 8.32407, -11.28685],
			"to": [11.62711, 8.87216, -10.73876],
			"rotation": {
				"angle": 22.5,
				"axis": "x",
				"origin": [11.62494, 9.05123, -7.29725]
			},
			"faces": {
				"north": {
					"uv": [5.8, 7.9, 5.8, 7.9],
					"texture": "#0"
				},
				"east": {
					"uv": [5.8, 7.9, 5.8, 7.9],
					"texture": "#0"
				},
				"south": {
					"uv": [5.8, 7.9, 5.8, 7.9],
					"texture": "#0"
				},
				"west": {
					"uv": [5.8, 7.9, 5.8, 7.9],
					"texture": "#0"
				},
				"up": {
					"uv": [5.8, 7.9, 5.8, 7.9],
					"texture": "#0"
				},
				"down": {
					"uv": [5.8, 7.9, 5.8, 7.9],
					"texture": "#0"
				}
			}
		},
		{
			"from": [4.37289, 6.87409, -14.91179],
			"to": [4.55848, 7.42218, -14.3637],
			"rotation": {
				"angle": 22.5,
				"axis": "x",
				"origin": [4.55631, 7.60126, -10.92218]
			},
			"faces": {
				"north": {
					"uv": [5.8, 7.9, 5.8, 7.9],
					"texture": "#0"
				},
				"east": {
					"uv": [5.8, 7.9, 5.8, 7.9],
					"texture": "#0"
				},
				"south": {
					"uv": [5.8, 7.9, 5.8, 7.9],
					"texture": "#0"
				},
				"west": {
					"uv": [5.8, 7.9, 5.8, 7.9],
					"texture": "#0"
				},
				"up": {
					"uv": [5.8, 7.9, 5.8, 7.9],
					"texture": "#0"
				},
				"down": {
					"uv": [5.8, 7.9, 5.8, 7.9],
					"texture": "#0"
				}
			}
		},
		{
			"from": [4.37289, 7.23659, -14.00556],
			"to": [4.55848, 7.78468, -13.45747],
			"rotation": {
				"angle": 22.5,
				"axis": "x",
				"origin": [4.55631, 7.96375, -10.01595]
			},
			"faces": {
				"north": {
					"uv": [5.8, 7.9, 5.8, 7.9],
					"texture": "#0"
				},
				"east": {
					"uv": [5.8, 7.9, 5.8, 7.9],
					"texture": "#0"
				},
				"south": {
					"uv": [5.8, 7.9, 5.8, 7.9],
					"texture": "#0"
				},
				"west": {
					"uv": [5.8, 7.9, 5.8, 7.9],
					"texture": "#0"
				},
				"up": {
					"uv": [5.8, 7.9, 5.8, 7.9],
					"texture": "#0"
				},
				"down": {
					"uv": [5.8, 7.9, 5.8, 7.9],
					"texture": "#0"
				}
			}
		},
		{
			"from": [4.37289, 7.59908, -13.09932],
			"to": [4.55848, 8.14717, -12.55123],
			"rotation": {
				"angle": 22.5,
				"axis": "x",
				"origin": [4.55631, 8.32624, -9.10971]
			},
			"faces": {
				"north": {
					"uv": [5.8, 7.9, 5.8, 7.9],
					"texture": "#0"
				},
				"east": {
					"uv": [5.8, 7.9, 5.8, 7.9],
					"texture": "#0"
				},
				"south": {
					"uv": [5.8, 7.9, 5.8, 7.9],
					"texture": "#0"
				},
				"west": {
					"uv": [5.8, 7.9, 5.8, 7.9],
					"texture": "#0"
				},
				"up": {
					"uv": [5.8, 7.9, 5.8, 7.9],
					"texture": "#0"
				},
				"down": {
					"uv": [5.8, 7.9, 5.8, 7.9],
					"texture": "#0"
				}
			}
		},
		{
			"from": [4.37289, 7.96158, -12.19309],
			"to": [4.55848, 8.50967, -11.645],
			"rotation": {
				"angle": 22.5,
				"axis": "x",
				"origin": [4.55631, 8.68874, -8.20348]
			},
			"faces": {
				"north": {
					"uv": [5.8, 7.9, 5.8, 7.9],
					"texture": "#0"
				},
				"east": {
					"uv": [5.8, 7.9, 5.8, 7.9],
					"texture": "#0"
				},
				"south": {
					"uv": [5.8, 7.9, 5.8, 7.9],
					"texture": "#0"
				},
				"west": {
					"uv": [5.8, 7.9, 5.8, 7.9],
					"texture": "#0"
				},
				"up": {
					"uv": [5.8, 7.9, 5.8, 7.9],
					"texture": "#0"
				},
				"down": {
					"uv": [5.8, 7.9, 5.8, 7.9],
					"texture": "#0"
				}
			}
		},
		{
			"from": [4.37289, 8.32407, -11.28685],
			"to": [4.55848, 8.87216, -10.73876],
			"rotation": {
				"angle": 22.5,
				"axis": "x",
				"origin": [4.55631, 9.05123, -7.29725]
			},
			"faces": {
				"north": {
					"uv": [5.8, 7.9, 5.8, 7.9],
					"texture": "#0"
				},
				"east": {
					"uv": [5.8, 7.9, 5.8, 7.9],
					"texture": "#0"
				},
				"south": {
					"uv": [5.8, 7.9, 5.8, 7.9],
					"texture": "#0"
				},
				"west": {
					"uv": [5.8, 7.9, 5.8, 7.9],
					"texture": "#0"
				},
				"up": {
					"uv": [5.8, 7.9, 5.8, 7.9],
					"texture": "#0"
				},
				"down": {
					"uv": [5.8, 7.9, 5.8, 7.9],
					"texture": "#0"
				}
			}
		},
		{
			"from": [10.35404, 7.96158, -15.27429],
			"to": [11.26462, 8.69091, -15.08869],
			"rotation": {
				"angle": 45,
				"axis": "z",
				"origin": [11.0812, 8.50749, -11.64717]
			},
			"faces": {
				"north": {
					"uv": [5.8, 7.9, 5.9, 8],
					"texture": "#0"
				},
				"east": {
					"uv": [5.8, 7.9, 5.8, 8],
					"texture": "#0"
				},
				"south": {
					"uv": [5.9, 7.9, 6, 8],
					"texture": "#0"
				},
				"west": {
					"uv": [5.9, 7.9, 5.9, 8],
					"texture": "#0"
				},
				"up": {
					"uv": [5.9, 7.9, 5.8, 7.9],
					"texture": "#0"
				},
				"down": {
					"uv": [6, 7.9, 5.9, 7.9],
					"texture": "#0"
				}
			}
		},
		{
			"from": [9.26655, 7.96158, -15.27429],
			"to": [10.17714, 8.69091, -15.08869],
			"rotation": {
				"angle": 45,
				"axis": "z",
				"origin": [9.99372, 8.50749, -11.64717]
			},
			"faces": {
				"north": {
					"uv": [5.8, 8, 5.9, 8.1],
					"texture": "#0"
				},
				"east": {
					"uv": [5.8, 8, 5.8, 8.1],
					"texture": "#0"
				},
				"south": {
					"uv": [5.9, 8, 6, 8.1],
					"texture": "#0"
				},
				"west": {
					"uv": [5.9, 8, 5.9, 8.1],
					"texture": "#0"
				},
				"up": {
					"uv": [5.9, 8, 5.8, 8],
					"texture": "#0"
				},
				"down": {
					"uv": [6, 8, 5.9, 8],
					"texture": "#0"
				}
			}
		},
		{
			"from": [7.99783, 7.96158, -15.27429],
			"to": [8.90841, 8.69091, -15.08869],
			"rotation": {
				"angle": 45,
				"axis": "z",
				"origin": [8.72499, 8.50749, -11.64717]
			},
			"faces": {
				"north": {
					"uv": [5.7, 8, 5.8, 8.1],
					"texture": "#0"
				},
				"east": {
					"uv": [5.7, 8, 5.7, 8.1],
					"texture": "#0"
				},
				"south": {
					"uv": [5.8, 8, 5.9, 8.1],
					"texture": "#0"
				},
				"west": {
					"uv": [5.8, 8, 5.8, 8.1],
					"texture": "#0"
				},
				"up": {
					"uv": [5.8, 8, 5.7, 8],
					"texture": "#0"
				},
				"down": {
					"uv": [5.9, 8, 5.8, 8],
					"texture": "#0"
				}
			}
		},
		{
			"from": [6.7291, 7.96158, -15.27429],
			"to": [7.63968, 8.69091, -15.08869],
			"rotation": {
				"angle": 45,
				"axis": "z",
				"origin": [7.45626, 8.50749, -11.64717]
			},
			"faces": {
				"north": {
					"uv": [5.7, 7.9, 5.8, 8],
					"texture": "#0"
				},
				"east": {
					"uv": [5.7, 7.9, 5.7, 8],
					"texture": "#0"
				},
				"south": {
					"uv": [5.8, 7.9, 5.9, 8],
					"texture": "#0"
				},
				"west": {
					"uv": [5.8, 7.9, 5.8, 8],
					"texture": "#0"
				},
				"up": {
					"uv": [5.8, 7.9, 5.7, 7.9],
					"texture": "#0"
				},
				"down": {
					"uv": [5.9, 7.9, 5.8, 7.9],
					"texture": "#0"
				}
			}
		},
		{
			"from": [5.46037, 7.96158, -15.27429],
			"to": [6.37095, 8.69091, -15.08869],
			"rotation": {
				"angle": 45,
				"axis": "z",
				"origin": [6.18753, 8.50749, -11.64717]
			},
			"faces": {
				"north": {
					"uv": [5.7, 7.9, 5.8, 8],
					"texture": "#0"
				},
				"east": {
					"uv": [5.7, 7.9, 5.7, 8],
					"texture": "#0"
				},
				"south": {
					"uv": [5.8, 7.9, 5.9, 8],
					"texture": "#0"
				},
				"west": {
					"uv": [5.8, 7.9, 5.8, 8],
					"texture": "#0"
				},
				"up": {
					"uv": [5.8, 7.9, 5.7, 7.9],
					"texture": "#0"
				},
				"down": {
					"uv": [5.9, 7.9, 5.8, 7.9],
					"texture": "#0"
				}
			}
		},
		{
			"from": [4.19164, 7.96158, -15.27429],
			"to": [5.10222, 8.69091, -15.08869],
			"rotation": {
				"angle": 45,
				"axis": "z",
				"origin": [4.9188, 8.50749, -11.64717]
			},
			"faces": {
				"north": {
					"uv": [5.7, 8, 5.8, 8.1],
					"texture": "#0"
				},
				"east": {
					"uv": [5.7, 8, 5.7, 8.1],
					"texture": "#0"
				},
				"south": {
					"uv": [5.8, 8, 5.9, 8.1],
					"texture": "#0"
				},
				"west": {
					"uv": [5.8, 8, 5.8, 8.1],
					"texture": "#0"
				},
				"up": {
					"uv": [5.8, 8, 5.7, 8],
					"texture": "#0"
				},
				"down": {
					"uv": [5.9, 8, 5.8, 8],
					"texture": "#0"
				}
			}
		}
	]
}